mpl_ornaments/__init__.py
mpl_ornaments/titles.py
mpl_ornaments-0.0.4.dist-info/LICENSE
mpl_ornaments-0.0.4.dist-info/METADATA
mpl_ornaments-0.0.4.dist-info/WHEEL
mpl_ornaments-0.0.4.dist-info/top_level.txt
mpl_ornaments-0.0.4.dist-info/RECORD
